pyerualjetwork/__init__.py
pyerualjetwork/ene.py
pyerualjetwork/fitness_functions.py
pyerualjetwork/help.py
pyerualjetwork/issue_solver.py
pyerualjetwork/memory_ops.py
pyerualjetwork/model_ops.py
pyerualjetwork/nn.py
pyerualjetwork/old_cpu_model_ops.py
pyerualjetwork/old_cuda_model_ops.py
pyerualjetwork/ui.py
pyerualjetwork/cpu/__init__.py
pyerualjetwork/cpu/activation_functions.py
pyerualjetwork/cpu/data_ops.py
pyerualjetwork/cpu/loss_functions.py
pyerualjetwork/cpu/metrics.py
pyerualjetwork/cpu/visualizations.py
pyerualjetwork/cuda/__init__.py
pyerualjetwork/cuda/activation_functions.py
pyerualjetwork/cuda/data_ops.py
pyerualjetwork/cuda/loss_functions.py
pyerualjetwork/cuda/metrics.py
pyerualjetwork/cuda/visualizations.py
pyerualjetwork-5.53.dist-info/METADATA
pyerualjetwork-5.53.dist-info/WHEEL
pyerualjetwork-5.53.dist-info/top_level.txt
pyerualjetwork-5.53.dist-info/RECORD
